zope/pluggableauth/README.rst
zope/pluggableauth/__init__.py
zope/pluggableauth/authentication.py
zope/pluggableauth/configure.zcml
zope/pluggableauth/factories.py
zope/pluggableauth/interfaces.py
zope/pluggableauth/principalfactories.zcml
zope/pluggableauth/tests.py
zope/pluggableauth/plugins/__init__.py
zope/pluggableauth/plugins/ftpplugins.py
zope/pluggableauth/plugins/ftpplugins.zcml
zope/pluggableauth/plugins/generic.py
zope/pluggableauth/plugins/generic.zcml
zope/pluggableauth/plugins/groupfolder.py
zope/pluggableauth/plugins/groupfolder.rst
zope/pluggableauth/plugins/groupfolder.zcml
zope/pluggableauth/plugins/httpplugins.py
zope/pluggableauth/plugins/httpplugins.zcml
zope/pluggableauth/plugins/idpicker.py
zope/pluggableauth/plugins/principalfolder.py
zope/pluggableauth/plugins/principalfolder.rst
zope/pluggableauth/plugins/principalfolder.zcml
zope/pluggableauth/plugins/session.py
zope/pluggableauth/plugins/session.zcml
zope_pluggableauth-5.0.dist-info/licenses/LICENSE.txt
zope_pluggableauth-5.0.dist-info/METADATA
zope_pluggableauth-5.0.dist-info/WHEEL
zope_pluggableauth-5.0.dist-info/top_level.txt
zope_pluggableauth-5.0.dist-info/RECORD
