Metadata-Version: 2.4
Name: zope.pluggableauth
Version: 5.0
Summary: Pluggable Authentication Utility
Home-page: https://github.com/zopefoundation/zope.pluggableauth
Author: Zope Foundation and Contributors
Author-email: zope-dev@zope.dev
License: ZPL-2.1
Keywords: zope3 ztk authentication pluggable
Classifier: Development Status :: 5 - Production/Stable
Classifier: Environment :: Web Environment
Classifier: Intended Audience :: Developers
Classifier: License :: OSI Approved :: Zope Public License
Classifier: Programming Language :: Python
Classifier: Programming Language :: Python :: 3
Classifier: Programming Language :: Python :: 3.9
Classifier: Programming Language :: Python :: 3.10
Classifier: Programming Language :: Python :: 3.11
Classifier: Programming Language :: Python :: 3.12
Classifier: Programming Language :: Python :: 3.13
Classifier: Programming Language :: Python :: Implementation :: CPython
Classifier: Programming Language :: Python :: Implementation :: PyPy
Classifier: Natural Language :: English
Classifier: Operating System :: OS Independent
Classifier: Topic :: Internet :: WWW/HTTP
Classifier: Framework :: Zope :: 3
Requires-Python: >=3.9
License-File: LICENSE.txt
Requires-Dist: persistent
Requires-Dist: setuptools
Requires-Dist: transaction
Requires-Dist: zope.authentication
Requires-Dist: zope.component
Requires-Dist: zope.container
Requires-Dist: zope.event
Requires-Dist: zope.i18nmessageid
Requires-Dist: zope.interface
Requires-Dist: zope.password>=3.5.1
Requires-Dist: zope.publisher>=3.12
Requires-Dist: zope.schema
Requires-Dist: zope.security
Requires-Dist: zope.session
Requires-Dist: zope.site
Requires-Dist: zope.traversing
Provides-Extra: test
Requires-Dist: zope.testing; extra == "test"
Requires-Dist: zope.testrunner>=6.4; extra == "test"
Dynamic: author
Dynamic: author-email
Dynamic: classifier
Dynamic: description
Dynamic: home-page
Dynamic: keywords
Dynamic: license
Dynamic: license-file
Dynamic: provides-extra
Dynamic: requires-dist
Dynamic: requires-python
Dynamic: summary
